idfy_sdk/__init__.py
idfy_sdk/urls.py
idfy_sdk/version.py
idfy_sdk/idfy_configuration/__init__.py
idfy_sdk/idfy_configuration/idfy_configuration.py
idfy_sdk/idfy_configuration/meta_idfy_configuration.py
idfy_sdk/infrastructure/AuthManager.py
idfy_sdk/infrastructure/__init__.py
idfy_sdk/infrastructure/http_requests.py
idfy_sdk/infrastructure/idfy_exception.py
idfy_sdk/infrastructure/serialization.py
idfy_sdk/infrastructure/models/__init__.py
idfy_sdk/infrastructure/models/oauth_token.py
idfy_sdk/services/IdfyBaseService.py
idfy_sdk/services/__init__.py
idfy_sdk/services/admin/__init__.py
idfy_sdk/services/admin/admin_service.py
idfy_sdk/services/admin/models/__init__.py
idfy_sdk/services/admin/models/account.py
idfy_sdk/services/admin/models/account_list_item.py
idfy_sdk/services/admin/models/account_logo.py
idfy_sdk/services/admin/models/account_name_item.py
idfy_sdk/services/admin/models/account_search_filter.py
idfy_sdk/services/admin/models/address.py
idfy_sdk/services/admin/models/claim_lite.py
idfy_sdk/services/admin/models/contact.py
idfy_sdk/services/admin/models/create_account_request.py
idfy_sdk/services/admin/models/create_oauth_api_client_request.py
idfy_sdk/services/admin/models/create_open_id_client_request.py
idfy_sdk/services/admin/models/create_pdf_template.py
idfy_sdk/services/admin/models/create_pdf_template_details_page_html.py
idfy_sdk/services/admin/models/create_pdf_template_labels.py
idfy_sdk/services/admin/models/create_pdf_template_verified_template.py
idfy_sdk/services/admin/models/dealer.py
idfy_sdk/services/admin/models/dealer_info.py
idfy_sdk/services/admin/models/dealer_logo.py
idfy_sdk/services/admin/models/oauth_api_client_response.py
idfy_sdk/services/admin/models/oauth_client_id.py
idfy_sdk/services/admin/models/oauth_client_list_item_response.py
idfy_sdk/services/admin/models/oauth_secret.py
idfy_sdk/services/admin/models/onboarding.py
idfy_sdk/services/admin/models/open_id_client_response.py
idfy_sdk-1.1.0.dist-info/LICENSE
idfy_sdk-1.1.0.dist-info/METADATA
idfy_sdk-1.1.0.dist-info/WHEEL
idfy_sdk-1.1.0.dist-info/top_level.txt
idfy_sdk-1.1.0.dist-info/RECORD
