Metadata-Version: 2.1
Name: idfy-sdk
Version: 1.1.0
Summary: SDK for using the Idfy API in Python
Home-page: https://github.com/idfy-io/idfy-sdk-python
Author: Idfy
Author-email: support@idfy.io
License: UNKNOWN
Platform: UNKNOWN
Classifier: Programming Language :: Python :: 3
Classifier: License :: OSI Approved :: MIT License
Classifier: Operating System :: OS Independent
Requires-Dist: Requests
